transformertopic/__init__.py
transformertopic/transformertopic.py
transformertopic/clusterRepresentators/__init__.py
transformertopic/clusterRepresentators/kmaxoids.py
transformertopic/clusterRepresentators/textrank.py
transformertopic/clusterRepresentators/tfidf.py
transformertopic/dimensionReducers/__init__.py
transformertopic/dimensionReducers/pacmapEmbeddings.py
transformertopic/dimensionReducers/tsneEmbeddings.py
transformertopic/dimensionReducers/umapEmbeddings.py
transformertopic/utils/__init__.py
transformertopic/utils/generateTextId.py
transformertopic/utils/scrambleDates.py
transformertopic/utils/wordclouds.py
transformertopic-1.8.dist-info/LICENSE
transformertopic-1.8.dist-info/METADATA
transformertopic-1.8.dist-info/WHEEL
transformertopic-1.8.dist-info/top_level.txt
transformertopic-1.8.dist-info/RECORD
