Metadata-Version: 2.1
Name: transformertopic
Version: 1.8
Summary: Topic modeling using sentence_transformer
Home-page: https://github.com/nareto/transformertopic
Author: Renato Budinich
Author-email: rennabh@gmail.com
License: MIT
Platform: UNKNOWN
Requires-Dist: hdbscan
Requires-Dist: loguru
Requires-Dist: numpy
Requires-Dist: pacmap
Requires-Dist: pytextrank
Requires-Dist: seaborn
Requires-Dist: sentence-transformers
Requires-Dist: umap-learn
